{
  "date": "01-juillet-2025-mardi",
  "entries": [
    {
      "section": "Service",
      "number": "21",
      "name": "Caroline Jacques",
      "points": "10",
      "in": "16:30",
      "out": "21:30",
      "hours": "5.00"
    },
    {
      "section": "Service",
      "number": "99",
      "name": "Josée Lacroix",
      "points": "7",
      "in": "15:30",
      "out": "21:30",
      "hours": "6.00"
    },
    {
      "section": "Service",
      "number": "45",
      "name": "Lucas Di Loreto",
      "points": "7",
      "in": "09:30",
      "out": "15:30",
      "hours": "6.00"
    },
    {
      "section": "Bussboy",
      "number": "6",
      "name": "Sandrine Campeau",
      "points": "4",
      "in": "09:30",
      "out": "16:30",
      "hours": "7.00"
    },
    {
      "section": "Bussboy",
      "number": "1749",
      "name": "Charles Desrosiers",
      "points": "3",
      "in": "08:30",
      "out": "16:30",
      "hours": "8.00"
    }
  ]
}